{
 "sections": [
  {
   "id": "699d0e31-ed00-097a-c0a5-4ba19a6418d1",
   "title": "HTML/CSS/JS",
   "files": [
    {
     "path": "#tabs",
     "action": "close"
    },
    {
     "path": "index.html",
     "panel": 0,
     "action": "open"
    },
    {
     "path": "style.css",
     "panel": 0,
     "action": "open"
    },
    {
     "path": "sketch.js",
     "panel": 0,
     "action": "open"
    },
    {
     "path": "#preview: index.html",
     "panel": 1,
     "action": "open"
    }
   ],
   "layout": "3-columns",
   "path": [],
   "type": "markdown",
   "content-file": ".guides/content/HTML-CSS-JS-699d.md",
   "chapter": false,
   "reset": [],
   "teacherOnly": false,
   "learningObjectives": ""
  },
  {
   "id": "8b1e5d45-3b8b-37f0-e492-0591dec324de",
   "title": "Building the Page - Files",
   "files": [
    {
     "path": "#tabs",
     "action": "close"
    },
    {
     "path": "index.html",
     "panel": 0,
     "action": "open"
    },
    {
     "path": "style.css",
     "panel": 0,
     "action": "open"
    },
    {
     "path": "sketch.js",
     "panel": 0,
     "action": "open"
    },
    {
     "path": "#preview: index.html",
     "panel": 1,
     "action": "open"
    }
   ],
   "layout": "3-columns",
   "path": [],
   "type": "markdown",
   "content-file": ".guides/content/Building-the-Page---Files-8b1e.md",
   "chapter": false,
   "reset": [],
   "teacherOnly": false,
   "learningObjectives": ""
  },
  {
   "id": "e6b1cc5e-4210-e27f-0377-4872f2c1d256",
   "title": "Building the Page - Layout",
   "files": [
    {
     "path": "#tabs",
     "action": "close"
    },
    {
     "path": "index.html",
     "panel": 0,
     "action": "open"
    },
    {
     "path": "style.css",
     "panel": 0,
     "action": "open"
    },
    {
     "path": "sketch.js",
     "panel": 0,
     "action": "open"
    },
    {
     "path": "#preview: index.html",
     "panel": 1,
     "action": "open"
    }
   ],
   "layout": "3-columns",
   "path": [],
   "type": "markdown",
   "content-file": ".guides/content/Building-the-Page---Layout-e6b1.md",
   "chapter": false,
   "reset": [],
   "teacherOnly": false,
   "learningObjectives": ""
  },
  {
   "id": "de7f6b1c-d08e-c2e0-5038-7cef38068009",
   "title": "Building the Page - Opening Files",
   "files": [],
   "path": [],
   "type": "markdown",
   "content-file": ".guides/content/Building-the-Page---Opening-Files-de7f.md",
   "chapter": false,
   "reset": [],
   "teacherOnly": false,
   "learningObjectives": ""
  },
  {
   "id": "99679422-7b26-b0b1-3f4a-2afb77f559ef",
   "title": "Building the Page - Viewing Output",
   "files": [],
   "path": [],
   "type": "markdown",
   "content-file": ".guides/content/Building-the-Page---Viewing-Output-9967.md",
   "chapter": false,
   "reset": [],
   "teacherOnly": false,
   "learningObjectives": ""
  },
  {
   "id": "f39274ab-f55a-737b-cd9f-1c7e7fe53c93",
   "title": "Auto-Graded Assessments",
   "files": [
    {
     "path": "#tabs",
     "action": "close"
    }
   ],
   "layout": "1-panel",
   "path": [],
   "type": "markdown",
   "content-file": ".guides/content/Auto-Graded-Assessments-f392.md",
   "chapter": false,
   "reset": [],
   "teacherOnly": false,
   "learningObjectives": ""
  },
  {
   "id": "6dd85aa0-9766-b11a-0ea3-c1cf473958eb",
   "title": "DOM Manipulation Testing - Requirements",
   "files": [
    {
     "path": "#tabs",
     "action": "close"
    }
   ],
   "layout": "1-panel",
   "path": [],
   "type": "markdown",
   "content-file": ".guides/content/DOM-Manipulation-Testing---Requirements-6dd8.md",
   "chapter": false,
   "reset": [],
   "teacherOnly": false,
   "learningObjectives": ""
  },
  {
   "id": "6fd608fd-ca1d-857c-a9f1-93c4978b1a62",
   "title": "DOM Manipulation Testing - Function",
   "files": [
    {
     "path": "#tabs",
     "action": "close"
    },
    {
     "path": "dom-manipulation.js",
     "panel": 0,
     "action": "open"
    }
   ],
   "layout": "2-panels",
   "path": [],
   "type": "markdown",
   "content-file": ".guides/content/DOM-Manipulation-Testing---Function-6fd6.md",
   "chapter": false,
   "reset": [],
   "teacherOnly": false,
   "learningObjectives": ""
  },
  {
   "id": "26ee17d3-fa64-f823-c696-682dd36ebf96",
   "title": "DOM Manipulation Testing - Testing",
   "files": [
    {
     "path": "#tabs",
     "action": "close"
    },
    {
     "path": "dom-manipulation-test.js",
     "panel": 0,
     "action": "open"
    },
    {
     "path": "#terminal: ",
     "panel": 1,
     "action": "open"
    }
   ],
   "layout": "3-cell",
   "path": [],
   "type": "markdown",
   "content-file": ".guides/content/DOM-Manipulation-Testing---Testing-26ee.md",
   "chapter": false,
   "reset": [],
   "teacherOnly": false,
   "learningObjectives": ""
  }
 ],
 "theme": "light",
 "scripts": [],
 "lexikonTopic": "",
 "suppressPageNumbering": false,
 "useSubmitButtons": true,
 "useMarkAsComplete": true,
 "hideMenu": false,
 "allowGuideClose": false,
 "collapsedOnStart": false,
 "hideSectionsToggle": false,
 "hideBackToDashboard": false,
 "protectLayout": false
}